nbsee/__init__.py
nbsee/__main__.py
nbsee/textual_app.py
nbsee-0.1.2.dist-info/licenses/LICENSE
nbsee-0.1.2.dist-info/METADATA
nbsee-0.1.2.dist-info/WHEEL
nbsee-0.1.2.dist-info/entry_points.txt
nbsee-0.1.2.dist-info/top_level.txt
nbsee-0.1.2.dist-info/RECORD
