Metadata-Version: 2.4
Name: nbsee
Version: 0.1.2
Summary: Rich/Textual terminal viewer for Jupyter notebooks focused on copying code and text outputs
Author: Yoga Yudistira
License-Expression: MIT
Project-URL: Homepage, https://github.com/AnakTeka/nbsee
Project-URL: Repository, https://github.com/AnakTeka/nbsee
Project-URL: Issues, https://github.com/AnakTeka/nbsee/issues
Keywords: jupyter,notebook,cli,tui,rich,textual
Classifier: Programming Language :: Python :: 3
Classifier: Programming Language :: Python :: 3 :: Only
Classifier: Programming Language :: Python :: 3.10
Classifier: Programming Language :: Python :: 3.11
Classifier: Programming Language :: Python :: 3.12
Classifier: Environment :: Console
Classifier: Topic :: Utilities
Requires-Python: >=3.10
License-File: LICENSE
Requires-Dist: rich>=13.7
Requires-Dist: textual>=0.58
Dynamic: license-file
